detaframe/__init__.py
detaframe/annotations.py
detaframe/app.py
detaframe/component.py
detaframe/ctx.py
detaframe/db.py
detaframe/element.py
detaframe/enums.py
detaframe/form.py
detaframe/functions.py
detaframe/jinja.py
detaframe/keymodel.py
detaframe/metadata.py
detaframe/middleware.py
detaframe/model.py
detaframe/regex.py
detaframe-0.1.1.dist-info/WHEEL
detaframe-0.1.1.dist-info/METADATA
detaframe-0.1.1.dist-info/RECORD
