Metadata-Version: 2.1
Name: detaframe
Version: 0.1.1
Summary: Framework for DetaSpace using Pydantic and Starlette.
License: MIT
Author: Daniel Arantes
Author-email: arantesdv@me.com
Requires-Python: >=3.9,<4.0
Classifier: License :: OSI Approved :: MIT License
Classifier: Programming Language :: Python :: 3
Classifier: Programming Language :: Python :: 3.10
Classifier: Programming Language :: Python :: 3.9
Requires-Dist: Jinja2 (>=3.1.2,<4.0.0)
Requires-Dist: Unidecode (>=1.3.6,<2.0.0)
Requires-Dist: aiohttp (>=3.8.5,<4.0.0)
Requires-Dist: bcrypt (>=4.0.1,<5.0.0)
Requires-Dist: deta[async] (>=1.2.0,<2.0.0)
Requires-Dist: itsdangerous (>=2.1.2,<3.0.0)
Requires-Dist: pydantic (>=2.3.0,<3.0.0)
Requires-Dist: python-multipart (>=0.0.6,<0.0.7)
Requires-Dist: starlette (>=0.31.1,<0.32.0)
Requires-Dist: starlette-csrf (>=3.0.0,<4.0.0)
Requires-Dist: typing-extensions (>=4.7.1,<5.0.0)
Requires-Dist: uvicorn (>=0.23.2,<0.24.0)
